keep_gpu/__init__.py
keep_gpu/benchmark.py
keep_gpu/cli.py
keep_gpu/global_gpu_controller/__init__.py
keep_gpu/global_gpu_controller/global_gpu_controller.py
keep_gpu/single_gpu_controller/__init__.py
keep_gpu/single_gpu_controller/base_gpu_controller.py
keep_gpu/single_gpu_controller/cuda_gpu_controller.py
keep_gpu/single_gpu_controller/rocm_gpu_controller.py
keep_gpu/utilities/__init__.py
keep_gpu/utilities/gpu_monitor.py
keep_gpu/utilities/humanized_input.py
keep_gpu/utilities/logger.py
keep_gpu/utilities/platform_manager.py
keep_gpu-0.3.2.dist-info/licenses/LICENSE
keep_gpu-0.3.2.dist-info/METADATA
keep_gpu-0.3.2.dist-info/WHEEL
keep_gpu-0.3.2.dist-info/entry_points.txt
keep_gpu-0.3.2.dist-info/top_level.txt
keep_gpu-0.3.2.dist-info/RECORD
