Metadata-Version: 2.4
Name: keep_gpu
Version: 0.3.2
Summary: Keep GPU is a simple CLI app that keeps your GPUs running
Author-email: Siyuan Wang <sywang0227@gmail.com>, Yaorui Shi <yaoruishi@gmail.com>, Yiduck Liu <geodesicseiran@gmail.com>
Maintainer-email: Siyuan Wang <sywang0227@gmail.com>, Yaorui Shi <yaoruishi@gmail.com>, Yiduck Liu <geodesicseiran@gmail.com>
License: MIT license
Project-URL: bugs, https://github.com/Wangmerlyn/KeepGPU/issues
Project-URL: changelog, https://github.com/Wangmerlyn/KeepGPU/blob/master/changelog.md
Project-URL: homepage, https://github.com/Wangmerlyn/KeepGPU
License-File: LICENSE
Requires-Dist: nvidia-ml-py
Requires-Dist: typer
Requires-Dist: torch
Requires-Dist: colorlog
Provides-Extra: dev
Requires-Dist: coverage; extra == "dev"
Requires-Dist: mypy; extra == "dev"
Requires-Dist: pytest; extra == "dev"
Requires-Dist: ruff; extra == "dev"
Requires-Dist: black; extra == "dev"
Requires-Dist: pre-commit; extra == "dev"
Requires-Dist: bump-my-version; extra == "dev"
Dynamic: license-file
